[
    {
        "key": "dbln",
        "value": "%7B%22100086547860102%22%3A%22Y8V8K8ey%22%7D",
        "domain": "facebook.com",
        "path": "/login/device-based/",
        "hostOnly": false,
        "creation": "2024-06-03T12:34:14.617Z",
        "lastAccessed": "2024-06-03T12:34:14.633Z"
    },
    {
        "key": "datr",
        "value": "SbVIZvuu4K_l5hhUNBBUB-qE",
        "domain": "facebook.com",
        "path": "/",
        "hostOnly": false,
        "creation": "2024-06-03T12:34:14.633Z",
        "lastAccessed": "2024-06-03T12:34:14.633Z"
    },
    {
        "key": "sb",
        "value": "SbVIZpD0em_Bj-OlrVLVsNDv",
        "domain": "facebook.com",
        "path": "/",
        "hostOnly": false,
        "creation": "2024-06-03T12:34:14.633Z",
        "lastAccessed": "2024-06-03T12:34:14.633Z"
    },
    {
        "key": "locale",
        "value": "bn_IN",
        "domain": "facebook.com",
        "path": "/",
        "hostOnly": false,
        "creation": "2024-06-03T12:34:14.633Z",
        "lastAccessed": "2024-06-03T12:34:14.633Z"
    },
    {
        "key": "ps_n",
        "value": "1",
        "domain": "facebook.com",
        "path": "/",
        "hostOnly": false,
        "creation": "2024-06-03T12:34:14.633Z",
        "lastAccessed": "2024-06-03T12:34:14.633Z"
    },
    {
        "key": "ps_l",
        "value": "1",
        "domain": "facebook.com",
        "path": "/",
        "hostOnly": false,
        "creation": "2024-06-03T12:34:14.633Z",
        "lastAccessed": "2024-06-03T12:34:14.633Z"
    },
    {
        "key": "wd",
        "value": "470x892",
        "domain": "facebook.com",
        "path": "/",
        "hostOnly": false,
        "creation": "2024-06-03T12:34:14.633Z",
        "lastAccessed": "2024-06-03T12:34:14.633Z"
    },
    {
        "key": "fr",
        "value": "0kGCWJJ5RK0CjItzA.AWVsQDbqFwBzr_tcDtssB4KHsBQ.BmSLVJ..AAA.0.0.BmXZUX.AWWbvoZycDI",
        "domain": "facebook.com",
        "path": "/",
        "hostOnly": false,
        "creation": "2024-06-03T12:34:14.633Z",
        "lastAccessed": "2024-06-03T12:34:14.633Z"
    },
    {
        "key": "c_user",
        "value": "100086547860102",
        "domain": "facebook.com",
        "path": "/",
        "hostOnly": false,
        "creation": "2024-06-03T12:34:14.633Z",
        "lastAccessed": "2024-06-03T12:34:14.633Z"
    },
    {
        "key": "xs",
        "value": "8%3AkEBK8-mIhDVXMg%3A2%3A1717409047%3A-1%3A5130",
        "domain": "facebook.com",
        "path": "/",
        "hostOnly": false,
        "creation": "2024-06-03T12:34:14.633Z",
        "lastAccessed": "2024-06-03T12:34:14.633Z"
    },
    {
        "key": "wl_cbv",
        "value": "v2%3Bclient_version%3A2518%3Btimestamp%3A1717419359",
        "domain": "facebook.com",
        "path": "/",
        "hostOnly": false,
        "creation": "2024-06-03T12:34:14.633Z",
        "lastAccessed": "2024-06-03T12:34:14.633Z"
    },
    {
        "key": "fbl_st",
        "value": "100425864%3BT%3A28623629",
        "domain": "facebook.com",
        "path": "/",
        "hostOnly": false,
        "creation": "2024-06-03T12:34:14.633Z",
        "lastAccessed": "2024-06-03T12:34:14.633Z"
    },
    {
        "key": "vpd",
        "value": "v1%3B892x470x1.5303868055343628",
        "domain": "facebook.com",
        "path": "/",
        "hostOnly": false,
        "creation": "2024-06-03T12:34:14.633Z",
        "lastAccessed": "2024-06-03T12:34:14.633Z"
    }
]
